django_prettyjson-0.4.0.dist-info/DESCRIPTION.rst
django_prettyjson-0.4.0.dist-info/METADATA
django_prettyjson-0.4.0.dist-info/RECORD
django_prettyjson-0.4.0.dist-info/WHEEL
django_prettyjson-0.4.0.dist-info/metadata.json
django_prettyjson-0.4.0.dist-info/top_level.txt
prettyjson/__init__.py
prettyjson/models.py
prettyjson/widgets.py
prettyjson/static/prettyjson/prettyjson.css
prettyjson/static/prettyjson/prettyjson.js
prettyjson/templates/prettyjson/base.html
prettyjson/templatetags/__init__.py
prettyjson/templatetags/prettyjson.py
