Metadata-Version: 2.0
Name: django-prettyjson
Version: 0.4.0
Summary: Enables pretty JSON viewer in Django forms, admin, or templates
Home-page: https://github.com/kevinmickey/django-prettyjson
Author: Kevin Mickey
Author-email: kwmickey@gmail.com
License: BSD
Keywords: django-prettyjson
Platform: UNKNOWN
Classifier: Development Status :: 3 - Alpha
Classifier: Framework :: Django
Classifier: Framework :: Django :: 1.8
Classifier: Framework :: Django :: 1.9
Classifier: Intended Audience :: Developers
Classifier: License :: OSI Approved :: BSD License
Classifier: Natural Language :: English
Classifier: Programming Language :: Python :: 2
Classifier: Programming Language :: Python :: 2.7
Classifier: Programming Language :: Python :: 3
Classifier: Programming Language :: Python :: 3.4
Classifier: Programming Language :: Python :: 3.5
Requires-Dist: django (>=1.8)
Requires-Dist: standardjson (>=0.3.1)
Requires-Dist: six (>=1.10.0)
